kivy_find_recipe_package/__init__.py
kivy_find_recipe_package/findmeals.kv
kivy_find_recipe_package/main.py
kivy_find_recipe_package-1.1.dist-info/LICENSE
kivy_find_recipe_package-1.1.dist-info/METADATA
kivy_find_recipe_package-1.1.dist-info/WHEEL
kivy_find_recipe_package-1.1.dist-info/entry_points.txt
kivy_find_recipe_package-1.1.dist-info/top_level.txt
kivy_find_recipe_package-1.1.dist-info/RECORD
