Metadata-Version: 2.1
Name: kivy-find-recipe-package
Version: 1.1
Summary: UNKNOWN
Home-page: UNKNOWN
Author: Daniel Kříž
License: MIT
Platform: UNKNOWN
License-File: LICENSE
Requires-Dist: kivy
